BMI_calc_pkg/__init__.py
BMI_calc_pkg/bmi_calc.py
bmi_calculator-0.0.2.dist-info/LICENSE
bmi_calculator-0.0.2.dist-info/METADATA
bmi_calculator-0.0.2.dist-info/WHEEL
bmi_calculator-0.0.2.dist-info/top_level.txt
bmi_calculator-0.0.2.dist-info/RECORD
